{
  "Katupiry": {
    "precio": 44000,
    "ingredientes": "Katupiry, muzzarella, salsa de tomate",
    "imagen": "img/katupiry.jpg"
  },
  "Pancho": {
    "precio": 42000,
    "ingredientes": "Salchicha, muzzarella, salsa de tomate",
    "imagen": "img/pancho.jpg"
  },
  "Panceta": {
    "precio": 45000,
    "ingredientes": "Panceta crocante, muzzarella, salsa de tomate",
    "imagen": "img/panceta.jpg"
  },
  "Napolitana (tomates, parmesano, perejil con ajo)": {
    "precio": 45000,
    "ingredientes": "Muzzarella, tomate en rodajas, parmesano, ajo y perejil",
    "imagen": "img/napolitana.jpg"
  },
  "Margarita (tomates y albahaca fresca)": {
    "precio": 42000,
    "ingredientes": "Muzzarella, tomate, albahaca fresca",
    "imagen": "img/margarita.jpg"
  },
  "Vegetariana (morrones, cebolla, tomates y choclo)": {
    "precio": 40000,
    "ingredientes": "Morrones, cebolla, tomates, choclo, muzzarella",
    "imagen": "img/vegetariana.jpg"
  },
  "Traviesa (morrones, choclo, tomates y panceta crocante)": {
    "precio": 48000,
    "ingredientes": "Morrones, choclo, tomates, panceta crocante, muzzarella",
    "imagen": "img/traviesa.jpg"
  },
  "Choripizza (trozos de chorizo, cebolla, aceitunas)": {
    "precio": 50000,
    "ingredientes": "Chorizo, cebolla, aceitunas negras, muzzarella",
    "imagen": "img/choripizza.jpg"
  },
  "Panceta con queso Cheddar": {
    "precio": 48000,
    "ingredientes": "Panceta, queso cheddar, muzzarella",
    "imagen": "img/pancetaconquesoCheddar.jpg"
  },
  "Alekei (pollo, katupiry, verduras)": {
    "precio": 54000,
    "ingredientes": "Pollo, katupiry, morrón, cebolla, tomate",
    "imagen": "img/alekei.jpg"
  },
  "4 Quesos (muza, azul, katupiry y queso paraguay)": {
    "precio": 52000,
    "ingredientes": "Muzzarella, queso azul, katupiry, queso Paraguay",
    "imagen": "img/4quesos.jpg"
  },
  "Mexicana (carne de lomito, cebolla, morrones, tomate y picante)": {
    "precio": 60000,
    "ingredientes": "Carne de lomito, cebolla, morrones, tomate, picante",
    "imagen": "img/mexicana.jpg"
  },
  "Encantada (choclo, katupiry y papas fritas)": {
    "precio": 52000,
    "ingredientes": "Choclo, katupiry, papas fritas, muzzarella",
    "imagen": "img/encantada.jpg"
  },
  "Alorico ité (carnes, verduras y panceta)": {
    "precio": 85000,
    "ingredientes": "Carnes mixtas, verduras salteadas, panceta crocante, muzzarella",
    "imagen": "img/aloricoite.jpg"
  },
  "Fugaza (cebolla caramelizada)": {
    "precio": 38000,
    "ingredientes": "Cebolla caramelizada, orégano, muzzarella",
    "imagen": "img/fugaza.jpg"
  },
  "Jamón": {
    "precio": 42000,
    "ingredientes": "Jamón cocido, muzzarella",
    "imagen": "img/jamon.jpg"
  },
  "Muzarella": {
    "precio": 35000,
    "ingredientes": "Muzzarella y salsa de tomate",
    "imagen": "img/muzarella.jpg"
  },
  "Peperonni": {
    "precio": 45000,
    "ingredientes": "Peperonni, muzzarella",
    "imagen": "img/peperonni.jpg"
  },
  "Choclo": {
    "precio": 40000,
    "ingredientes": "Choclo, muzzarella, salsa de tomate",
    "imagen": "img/choclo.jpg"
  }
}
